setup.py
SFSHelper/SFSDate.py
SFSHelper/__init__.py
sfs_helper.egg-info/PKG-INFO
sfs_helper.egg-info/SOURCES.txt
sfs_helper.egg-info/dependency_links.txt
sfs_helper.egg-info/top_level.txt