Metadata-Version: 1.0
Name: sfs-helper
Version: 1.0
Summary: Help SFSOFT Programmer Easy Python
Home-page: http://www.sf-soft.com
Author: zk
Author-email: dlzk@qq.com
License: UNKNOWN
Platform: UNKNOWN
